django-stubs/__init__.pyi
django-stubs/apps/__init__.pyi
django-stubs/apps/config.pyi
django-stubs/apps/registry.pyi
django-stubs/conf/__init__.pyi
django-stubs/conf/global_settings.pyi
django-stubs/conf/locale/__init__.pyi
django-stubs/conf/urls/__init__.pyi
django-stubs/conf/urls/i18n.pyi
django-stubs/conf/urls/static.pyi
django-stubs/contrib/__init__.pyi
django-stubs/contrib/admin/__init__.pyi
django-stubs/contrib/admin/actions.pyi
django-stubs/contrib/admin/apps.pyi
django-stubs/contrib/admin/checks.pyi
django-stubs/contrib/admin/decorators.pyi
django-stubs/contrib/admin/exceptions.pyi
django-stubs/contrib/admin/filters.pyi
django-stubs/contrib/admin/forms.pyi
django-stubs/contrib/admin/helpers.pyi
django-stubs/contrib/admin/migrations/__init__.pyi
django-stubs/contrib/admin/models.pyi
django-stubs/contrib/admin/options.pyi
django-stubs/contrib/admin/sites.pyi
django-stubs/contrib/admin/templatetags/__init__.pyi
django-stubs/contrib/admin/templatetags/admin_list.pyi
django-stubs/contrib/admin/templatetags/admin_modify.pyi
django-stubs/contrib/admin/templatetags/admin_static.pyi
django-stubs/contrib/admin/templatetags/admin_urls.pyi
django-stubs/contrib/admin/templatetags/base.pyi
django-stubs/contrib/admin/templatetags/log.pyi
django-stubs/contrib/admin/tests.pyi
django-stubs/contrib/admin/utils.pyi
django-stubs/contrib/admin/views/__init__.pyi
django-stubs/contrib/admin/views/autocomplete.pyi
django-stubs/contrib/admin/views/decorators.pyi
django-stubs/contrib/admin/views/main.pyi
django-stubs/contrib/admin/widgets.pyi
django-stubs/contrib/admindocs/__init__.pyi
django-stubs/contrib/admindocs/apps.pyi
django-stubs/contrib/admindocs/middleware.pyi
django-stubs/contrib/admindocs/urls.pyi
django-stubs/contrib/admindocs/utils.pyi
django-stubs/contrib/admindocs/views.pyi
django-stubs/contrib/auth/__init__.pyi
django-stubs/contrib/auth/admin.pyi
django-stubs/contrib/auth/apps.pyi
django-stubs/contrib/auth/backends.pyi
django-stubs/contrib/auth/base_user.pyi
django_types-0.21.0.dist-info/LICENSE.txt
django_types-0.21.0.dist-info/METADATA
django_types-0.21.0.dist-info/WHEEL
django_types-0.21.0.dist-info/RECORD
