Metadata-Version: 2.3
Name: django-types
Version: 0.21.0
Summary: Type stubs for Django
License: MIT
Keywords: django,types,mypy,stubs
Author: Steve Dignam
Author-email: steve@dignam.xyz
Requires-Python: >=3.10,<4.0
Classifier: License :: OSI Approved :: MIT License
Classifier: Programming Language :: Python :: 3
Classifier: Programming Language :: Python :: 3.10
Classifier: Programming Language :: Python :: 3.11
Classifier: Programming Language :: Python :: 3.12
Classifier: Programming Language :: Python :: 3.13
Requires-Dist: types-psycopg2 (>=2.9.21.13)
Project-URL: Repository, https://github.com/sbdchd/django-types
